{
    "type": "FeatureCollection",
    "features": [
        {
            "type": "Feature",
            "geometry": {
                "type": "Point",
                "coordinates": [
                    4.900272,
                    52.3791283
                ]
            },
            "properties": {
                "Start": "Amsterdam",
                "End": "Munich",
                "stop_name": "Amsterdam",
                "latitude": 52.3791283,
                "longitude": 4.900272
            }
        },
        {
            "type": "Feature",
            "geometry": {
                "type": "Point",
                "coordinates": [
                    6.7769247,
                    51.429657
                ]
            },
            "properties": {
                "Start": "Amsterdam",
                "End": "Munich",
                "stop_name": "Duisburg Hbf",
                "latitude": 51.429657,
                "longitude": 6.7769247
            }
        },
        {
            "type": "Feature",
            "geometry": {
                "type": "Point",
                "coordinates": [
                    11.58022,
                    48.13913
                ]
            },
            "properties": {
                "Start": "Amsterdam",
                "End": "Munich",
                "stop_name": "Munich",
                "latitude": 48.13913,
                "longitude": 11.58022
            }
        }
    ]
}