{
    "type": "FeatureCollection",
    "features": [
        {
            "type": "Feature",
            "geometry": {
                "type": "Point",
                "coordinates": [
                    7.4354662,
                    46.9483506
                ]
            },
            "properties": {
                "Start": "Bern",
                "End": "Zagreb",
                "stop_name": "Bern",
                "latitude": 46.9483506,
                "longitude": 7.4354662
            }
        },
        {
            "type": "Feature",
            "geometry": {
                "type": "Point",
                "coordinates": [
                    8.5368921,
                    47.3785973
                ]
            },
            "properties": {
                "Start": "Bern",
                "End": "Zagreb",
                "stop_name": "Zurich, Switzerland",
                "latitude": 47.3785973,
                "longitude": 8.5368921
            }
        },
        {
            "type": "Feature",
            "geometry": {
                "type": "Point",
                "coordinates": [
                    15.97851,
                    45.81491
                ]
            },
            "properties": {
                "Start": "Bern",
                "End": "Zagreb",
                "stop_name": "Zagreb",
                "latitude": 45.81491,
                "longitude": 15.97851
            }
        }
    ]
}