{
    "type": "FeatureCollection",
    "features": [
        {
            "type": "Feature",
            "geometry": {
                "type": "Point",
                "coordinates": [
                    4.3570964,
                    50.845504
                ]
            },
            "properties": {
                "Start": "Brussels",
                "End": "Warsaw",
                "stop_name": "Brussels",
                "latitude": 50.845504,
                "longitude": 4.3570964
            }
        },
        {
            "type": "Feature",
            "geometry": {
                "type": "Point",
                "coordinates": [
                    8.5698462,
                    50.0528675
                ]
            },
            "properties": {
                "Start": "Brussels",
                "End": "Warsaw",
                "stop_name": "Frankfurt (Main) Airport Fernbahnhof",
                "latitude": 50.0528675,
                "longitude": 8.5698462
            }
        },
        {
            "type": "Feature",
            "geometry": {
                "type": "Point",
                "coordinates": [
                    13.369402,
                    52.5250839
                ]
            },
            "properties": {
                "Start": "Brussels",
                "End": "Warsaw",
                "stop_name": "Berlin Central Train Station",
                "latitude": 52.5250839,
                "longitude": 13.369402
            }
        },
        {
            "type": "Feature",
            "geometry": {
                "type": "Point",
                "coordinates": [
                    21.00849,
                    52.23498
                ]
            },
            "properties": {
                "Start": "Brussels",
                "End": "Warsaw",
                "stop_name": "Warsaw",
                "latitude": 52.23498,
                "longitude": 21.00849
            }
        }
    ]
}