{
    "type": "FeatureCollection",
    "features": [
        {
            "type": "Feature",
            "geometry": {
                "type": "Point",
                "coordinates": [
                    26.073892,
                    44.446634
                ]
            },
            "properties": {
                "Start": "Bucharest",
                "End": "Budapest",
                "stop_name": "Bucharest",
                "latitude": 44.446634,
                "longitude": 26.073892
            }
        },
        {
            "type": "Feature",
            "geometry": {
                "type": "Point",
                "coordinates": [
                    21.2376825,
                    46.4320143
                ]
            },
            "properties": {
                "Start": "Bucharest",
                "End": "Budapest",
                "stop_name": "L\u0151k\u00f6sh\u00e1za",
                "latitude": 46.4320143,
                "longitude": 21.2376825
            }
        },
        {
            "type": "Feature",
            "geometry": {
                "type": "Point",
                "coordinates": [
                    21.081542,
                    46.670041
                ]
            },
            "properties": {
                "Start": "Bucharest",
                "End": "Budapest",
                "stop_name": "B\u00e9k\u00e9scsaba",
                "latitude": 46.670041,
                "longitude": 21.081542
            }
        },
        {
            "type": "Feature",
            "geometry": {
                "type": "Point",
                "coordinates": [
                    19.04055,
                    47.49814
                ]
            },
            "properties": {
                "Start": "Bucharest",
                "End": "Budapest",
                "stop_name": "Budapest",
                "latitude": 47.49814,
                "longitude": 19.04055
            }
        }
    ]
}