{
    "type": "FeatureCollection",
    "features": [
        {
            "type": "Feature",
            "geometry": {
                "type": "Point",
                "coordinates": [
                    19.0577611,
                    47.510468
                ]
            },
            "properties": {
                "Start": "Budapest",
                "End": "Dresden",
                "stop_name": "Budapest",
                "latitude": 47.510468,
                "longitude": 19.0577611
            }
        },
        {
            "type": "Feature",
            "geometry": {
                "type": "Point",
                "coordinates": [
                    13.73363,
                    51.05099
                ]
            },
            "properties": {
                "Start": "Budapest",
                "End": "Dresden",
                "stop_name": "Dresden",
                "latitude": 51.05099,
                "longitude": 13.73363
            }
        }
    ]
}