{
    "type": "FeatureCollection",
    "features": [
        {
            "type": "Feature",
            "geometry": {
                "type": "Point",
                "coordinates": [
                    12.564617,
                    55.672722
                ]
            },
            "properties": {
                "Start": "Copenhagen",
                "End": "Munich",
                "stop_name": "Copenhagen",
                "latitude": 55.672722,
                "longitude": 12.564617
            }
        },
        {
            "type": "Feature",
            "geometry": {
                "type": "Point",
                "coordinates": [
                    10.0066369,
                    53.552993
                ]
            },
            "properties": {
                "Start": "Copenhagen",
                "End": "Munich",
                "stop_name": "Hamburg Central Station",
                "latitude": 53.552993,
                "longitude": 10.0066369
            }
        },
        {
            "type": "Feature",
            "geometry": {
                "type": "Point",
                "coordinates": [
                    11.58022,
                    48.13913
                ]
            },
            "properties": {
                "Start": "Copenhagen",
                "End": "Munich",
                "stop_name": "Munich",
                "latitude": 48.13913,
                "longitude": 11.58022
            }
        }
    ]
}