{
    "type": "FeatureCollection",
    "features": [
        {
            "type": "Feature",
            "geometry": {
                "type": "Point",
                "coordinates": [
                    14.5122127,
                    46.05823
                ]
            },
            "properties": {
                "Start": "Ljubljana",
                "End": "Rome",
                "stop_name": "Ljubljana",
                "latitude": 46.05823,
                "longitude": 14.5122127
            }
        },
        {
            "type": "Feature",
            "geometry": {
                "type": "Point",
                "coordinates": [
                    14.0548417,
                    46.4363972
                ]
            },
            "properties": {
                "Start": "Ljubljana",
                "End": "Rome",
                "stop_name": "Jesenice",
                "latitude": 46.4363972,
                "longitude": 14.0548417
            }
        },
        {
            "type": "Feature",
            "geometry": {
                "type": "Point",
                "coordinates": [
                    13.6350858,
                    45.9551478
                ]
            },
            "properties": {
                "Start": "Ljubljana",
                "End": "Rome",
                "stop_name": "Nova Gorica, Slovenia",
                "latitude": 45.9551478,
                "longitude": 13.6350858
            }
        },
        {
            "type": "Feature",
            "geometry": {
                "type": "Point",
                "coordinates": [
                    12.49427,
                    41.89056
                ]
            },
            "properties": {
                "Start": "Ljubljana",
                "End": "Rome",
                "stop_name": "Rome",
                "latitude": 41.89056,
                "longitude": 12.49427
            }
        }
    ]
}