{
    "type": "FeatureCollection",
    "features": [
        {
            "type": "Feature",
            "geometry": {
                "type": "Point",
                "coordinates": [
                    10.7568139,
                    59.9096203
                ]
            },
            "properties": {
                "Start": "Oslo",
                "End": "Stockholm",
                "stop_name": "Oslo",
                "latitude": 59.9096203,
                "longitude": 10.7568139
            }
        },
        {
            "type": "Feature",
            "geometry": {
                "type": "Point",
                "coordinates": [
                    18.06449,
                    59.33279
                ]
            },
            "properties": {
                "Start": "Oslo",
                "End": "Stockholm",
                "stop_name": "Stockholm",
                "latitude": 59.33279,
                "longitude": 18.06449
            }
        }
    ]
}