{
    "type": "FeatureCollection",
    "features": [
        {
            "type": "Feature",
            "geometry": {
                "type": "Point",
                "coordinates": [
                    14.4353058,
                    50.0832088
                ]
            },
            "properties": {
                "Start": "Prague",
                "End": "Rome",
                "stop_name": "Prague",
                "latitude": 50.0832088,
                "longitude": 14.4353058
            }
        },
        {
            "type": "Feature",
            "geometry": {
                "type": "Point",
                "coordinates": [
                    16.3765973,
                    48.1851873
                ]
            },
            "properties": {
                "Start": "Prague",
                "End": "Rome",
                "stop_name": "Vienna Central T",
                "latitude": 48.1851873,
                "longitude": 16.3765973
            }
        },
        {
            "type": "Feature",
            "geometry": {
                "type": "Point",
                "coordinates": [
                    11.8804541,
                    45.4173498
                ]
            },
            "properties": {
                "Start": "Prague",
                "End": "Rome",
                "stop_name": "Padova",
                "latitude": 45.4173498,
                "longitude": 11.8804541
            }
        },
        {
            "type": "Feature",
            "geometry": {
                "type": "Point",
                "coordinates": [
                    12.49427,
                    41.89056
                ]
            },
            "properties": {
                "Start": "Prague",
                "End": "Rome",
                "stop_name": "Rome",
                "latitude": 41.89056,
                "longitude": 12.49427
            }
        }
    ]
}