{
    "type": "FeatureCollection",
    "features": [
        {
            "type": "Feature",
            "geometry": {
                "type": "Point",
                "coordinates": [
                    16.3765973,
                    48.1851873
                ]
            },
            "properties": {
                "Start": "Vienna",
                "End": "Warsaw",
                "stop_name": "Vienna",
                "latitude": 48.1851873,
                "longitude": 16.3765973
            }
        },
        {
            "type": "Feature",
            "geometry": {
                "type": "Point",
                "coordinates": [
                    21.00849,
                    52.23498
                ]
            },
            "properties": {
                "Start": "Vienna",
                "End": "Warsaw",
                "stop_name": "Warsaw",
                "latitude": 52.23498,
                "longitude": 21.00849
            }
        }
    ]
}