{
    "type": "FeatureCollection",
    "features": [
        {
            "type": "Feature",
            "geometry": {
                "type": "Point",
                "coordinates": [
                    16.3765973,
                    48.1851873
                ]
            },
            "properties": {
                "Start": "Vienna",
                "End": "Vilnius",
                "stop_name": "Vienna",
                "latitude": 48.1851873,
                "longitude": 16.3765973
            }
        },
        {
            "type": "Feature",
            "geometry": {
                "type": "Point",
                "coordinates": [
                    18.6769,
                    50.30104
                ]
            },
            "properties": {
                "Start": "Vienna",
                "End": "Vilnius",
                "stop_name": "Gliwice",
                "latitude": 50.30104,
                "longitude": 18.6769
            }
        },
        {
            "type": "Feature",
            "geometry": {
                "type": "Point",
                "coordinates": [
                    20.2316667,
                    51.3586667
                ]
            },
            "properties": {
                "Start": "Vienna",
                "End": "Vilnius",
                "stop_name": "Opoczno Poludnie",
                "latitude": 51.3586667,
                "longitude": 20.2316667
            }
        },
        {
            "type": "Feature",
            "geometry": {
                "type": "Point",
                "coordinates": [
                    25.27986,
                    54.68946
                ]
            },
            "properties": {
                "Start": "Vienna",
                "End": "Vilnius",
                "stop_name": "Vilnius",
                "latitude": 54.68946,
                "longitude": 25.27986
            }
        }
    ]
}