{
    "type": "FeatureCollection",
    "features": [
        {
            "type": "Feature",
            "geometry": {
                "type": "Point",
                "coordinates": [
                    25.2842932,
                    54.6703567
                ]
            },
            "properties": {
                "Start": "Vilnius",
                "End": "Warsaw",
                "stop_name": "Vilnius",
                "latitude": 54.6703567,
                "longitude": 25.2842932
            }
        },
        {
            "type": "Feature",
            "geometry": {
                "type": "Point",
                "coordinates": [
                    23.932767,
                    54.8859184
                ]
            },
            "properties": {
                "Start": "Vilnius",
                "End": "Warsaw",
                "stop_name": "Kaunas, Lithuania",
                "latitude": 54.8859184,
                "longitude": 23.932767
            }
        },
        {
            "type": "Feature",
            "geometry": {
                "type": "Point",
                "coordinates": [
                    22.9224132,
                    54.0991957
                ]
            },
            "properties": {
                "Start": "Vilnius",
                "End": "Warsaw",
                "stop_name": "Suwalki, Poland",
                "latitude": 54.0991957,
                "longitude": 22.9224132
            }
        },
        {
            "type": "Feature",
            "geometry": {
                "type": "Point",
                "coordinates": [
                    21.00849,
                    52.23498
                ]
            },
            "properties": {
                "Start": "Vilnius",
                "End": "Warsaw",
                "stop_name": "Warsaw",
                "latitude": 52.23498,
                "longitude": 21.00849
            }
        }
    ]
}